{
  "title": "front-end development",
  "id": "00fc75f3-3eb3-40bf-b26f-c2bcfdc373fa",
  "published": false,
  "testEnvironment": "browser",
  "modules": [
    {
      "title": "front end overview",
      "id": "1062e696-c76a-46db-aaf8-849e7da62ed8",
      "checkpoint": false,
      "subModules": [
        {
          "title": "introduction",
          "id": "10cdbf75-af96-4348-8091-f7f849990719",
          "checkpoint": false,
          "lessons": [
            {
              "title": "definition and role",
              "id": "1c2f1c83-4a79-4ac9-b3e1-05fb584c6843"
            },
            {
              "title": "importance",
              "id": "2bd914fd-6e5e-4902-9864-a2a2dc62beec"
            },
            {
              "title": "key skills and technologies",
              "id": "3b77badc-f34a-4aa0-809d-1bb2f4379aad"
            }
          ]
        },
        {
          "title": "history",
          "id": "7a514543-dd22-4805-b5af-cc13b5ce0862",
          "checkpoint": false,
          "lessons": [
            {
              "title": "evolution of frontend technologies",
              "id": "b288c620-47da-4054-96ae-63f189960aa8"
            },
            {
              "title": "milstones in frontend development",
              "id": "6e04a3eb-85ab-482a-a345-399c39324b8e"
            }
          ]
        },
        {
          "title": "job opportunities",
          "id": "ddd28325-73de-49d7-94d5-4495101ea8be",
          "checkpoint": false,
          "lessons": [
            {
              "title": "career paths and job roles",
              "id": "5c920480-42b4-42ac-b8df-d6a2543e0577"
            },
            {
              "title": "skills and qualifications",
              "id": "da4acdc7-0ccd-40d5-8b27-fc24db13aa56"
            },
            {
              "title": "job outlook and trends",
              "id": "61acc35f-2ae6-460c-9a61-b246c6afb45f"
            }
          ]
        },
        {
          "title": "web standards",
          "id": "7076386b-7b45-4070-b374-74edd776f61a",
          "checkpoint": false,
          "lessons": [
            {
              "title": "definition and importance",
              "id": "cfbf9f3f-d4bf-49a6-b90a-ab1036e0c307"
            },
            {
              "title": "overview of key web standards organizations",
              "id": "fa10d63e-4c4f-4bdd-aed3-ed6e28d7afff"
            },
            {
              "title": "common web standards",
              "id": "75fa9499-6814-442a-86f8-f1182fc65546"
            }
          ]
        }
      ]
    },
    {
      "title": "the internet",
      "id": "72a53f40-688c-47b6-8127-ee6a67424c4d",
      "checkpoint": false,
      "subModules": [
        {
          "title": "how the internet works",
          "id": "c0595d0a-bb3d-4dd3-9ee8-b86a17f872c0",
          "checkpoint": false,
          "lessons": [
            {
              "title": "introduction",
              "id": "1cb4ab9f-2e09-4863-a002-588ae34cd4b9"
            },
            {
              "title": "concepts and terminologies",
              "id": "2dfab237-2e92-4fa2-b427-1546b62aff70"
            },
            {
              "title": "the role of protocols in internet",
              "id": "4a4dcd2a-e948-49d5-a134-3071c0ffb8ac"
            },
            {
              "title": "IP addresses and domain names",
              "id": "8550d004-4fb0-485b-ac96-eac05729d80d"
            },
            {
              "title": "Introduction to HTTP and HTTPS",
              "id": "3ab01879-ae95-44de-9067-52d181f866b5"
            },
            {
              "title": "Building applications with TCP/IP",
              "id": "d8e8c96d-f563-481b-ab61-abe8ca107b0e"
            },
            {
              "title": "Securing internet communication with SSL/TLS",
              "id": "ad057142-57bb-44c8-a0a8-18d6fd74c453"
            },
            {
              "title": "Emerging trends and technologies",
              "id": "7819ea41-5e94-4e76-9291-ea49071be526"
            }
          ]
        },
        {
          "title": "HTTP(s)",
          "id": "d628c417-9500-4f1c-9a14-15d4e8900605",
          "checkpoint": false,
          "lessons": [
            {
              "title": "overview",
              "id": "444bf13a-c73c-4059-85f0-490b2efeed19"
            },
            {
              "title": "HTTP/0.9",
              "id": "54b7abee-92b4-4cf2-b42a-407e297ed91d"
            },
            {
              "title": "HTTP/1.0",
              "id": "0a47866b-dab9-4217-a7bf-c7d29fa7379f"
            },
            {
              "title": "HTTP/1.1",
              "id": "37d288cd-61cd-4b08-8d62-65a936951396"
            },
            {
              "title": "SPDY",
              "id": "41123424-673c-4ac6-ad7a-800461ded33a"
            },
            {
              "title": "HTTP/2",
              "id": "0c640441-4318-4b0e-aa1b-c6a77f2dd796"
            },
            {
              "title": "HTTP/3",
              "id": "4c0d67b0-03f7-4411-aac4-dce5b9331d82"
            }
          ]
        }
      ]
    }
  ]
}